collectd/__init__.py
collectd/dispatcher.py
collectd/registry.py
python_collectd_mock-0.0.3.dist-info/METADATA
python_collectd_mock-0.0.3.dist-info/RECORD
python_collectd_mock-0.0.3.dist-info/WHEEL
python_collectd_mock-0.0.3.dist-info/top_level.txt
