Metadata-Version: 2.1
Name: python-collectd-mock
Version: 0.0.3
Summary: A python mock module for collectd plugin unittest test.
Home-page: https://github.com/winkidney/python-collectd-mock
Author: winkidney
Author-email: winkidney@gmail.com
License: UNKNOWN
Platform: UNKNOWN
Classifier: Topic :: Software Development :: Testing
